[{
  "id": 1,
  "crimg": "https://dynamic-media-cdn.tripadvisor.com/media/photo-o/16/1a/ea/54/hotel-presidente-4s.jpg?w=1400&h=-1&s=1",
  "category": "Hoteles",
  "title": "Hotel",
  "description": "Está situado a solo unas calles de la avenida Alvear, de la avenida Quintana, del parque San Martín y del distrito de Recoleta. En las inmediaciones también hay varios lugares de interés, como la calle Florida, el centro comercial Galerías Pacífico, la zona de Puerto Madero, la plaza de Mayo y el palacio Municipal.",
  "name": "Hermitage Hotel I",
  "score": "8",
  "location": {
    "city": "Buenos Aires, Ciudad Autónoma de Buenos Aires",
    "country": "Argentina",
    "address": "Thames & Charcas",
    "lat": -34.58282425124159, 
    "long": -58.423771223581824
  },
  "politica": [
    {
        "id": 2,
        "titulo": "Normas de la casa",
        "descripcion": "Check-out: 10:00\nNo se permiten fiestas\nNo fumar",
        "tipo_politica": "casa",
        "producto_id": 2
    },
    {
        "id": 3,
        "titulo": "Salud y seguridad",
        "descripcion": "Se aplican las pautas de distanciamiento social y otras normas relacionadas con el coronavirus",
        "tipo_politica": "seguridad",
        "producto_id": 2
    },
    {
        "id": 1,
        "titulo": "Política de cancelación",
        "descripcion": "Agregá las fechas de tu viaje para obtener los detalles de cancelación de esta estadía.",
        "tipo_politica": "cancelacion",
        "producto_id": 2
    }
],
  "caracteristicas": [
    {
      "id": 1,
      "nombre": "Cocina",
      "urlIcono": "https://bucket-imagenes-grupo2-0821-integrador.s3.amazonaws.com/icons/kitchen.svg"
    },
    {
      "id": 2,
      "nombre": "Estacionamiento gratuito",
      "urlIcono": "https://bucket-imagenes-grupo2-0821-integrador.s3.amazonaws.com/icons/car.svg"
    },
    {
      "id": 3,
      "nombre": "Televisor",
      "urlIcono": "https://bucket-imagenes-grupo2-0821-integrador.s3.amazonaws.com/icons/tv.svg"
    },
    {
      "id": 4,
      "nombre": "Pileta",
      "urlIcono": "https://bucket-imagenes-grupo2-0821-integrador.s3.amazonaws.com/icons/nadador.svg"
    },
    {
      "id": 5,
      "nombre": "Aire acondicionado",
      "urlIcono": "https://bucket-imagenes-grupo2-0821-integrador.s3.amazonaws.com/icons/air.svg"
    },
    {
      "id": 6,
      "nombre": "Wifi",
      "urlIcono": "https://bucket-imagenes-grupo2-0821-integrador.s3.amazonaws.com/icons/wifi.svg"
    },
    {
      "id": 7,
      "nombre": "Apto mascotas",
      "urlIcono": "https://bucket-imagenes-grupo2-0821-integrador.s3.amazonaws.com/icons/pet.svg"
    }
  ],
  "images": [
    {
      "id": 1,
      "urlImagen": "https://bucket-imagenes-grupo2-0821-integrador.s3.amazonaws.com/imagenesHoteles/room.jpg"
    },
    {
      "id": 2,
      "urlImagen": "https://bucket-imagenes-grupo2-0821-integrador.s3.amazonaws.com/imagenesHoteles/breakfast.jpg"
    },
    {
      "id": 3,
      "urlImagen": "https://bucket-imagenes-grupo2-0821-integrador.s3.amazonaws.com/imagenesHoteles/viewhotel.jpg"
    },
    {
      "id": 4,
      "urlImagen": "https://bucket-imagenes-grupo2-0821-integrador.s3.amazonaws.com/imagenesHoteles/sauna.jpg"
    },
    {
      "id": 5,
      "urlImagen": "https://bucket-imagenes-grupo2-0821-integrador.s3.amazonaws.com/imagenesHoteles/sunset.jpg"
    },
    {
      "id": 6,
      "urlImagen": "https://bucket-imagenes-grupo2-0821-integrador.s3.amazonaws.com/imagenesHoteles/comedor.jpg"
    },
    {
      "id": 7,
      "urlImagen": "https://bucket-imagenes-grupo2-0821-integrador.s3.amazonaws.com/imagenesHoteles/lobby.jpg"
    },
    {
      "id": 8,
      "urlImagen": "https://bucket-imagenes-grupo2-0821-integrador.s3.amazonaws.com/imagenesHoteles/salon.jpg"
    },
    {
      "id": 9,
      "urlImagen": "https://bucket-imagenes-grupo2-0821-integrador.s3.amazonaws.com/imagenesHoteles/hotel.jpg"
    },
    {
      "id": 10,
      "urlImagen": "https://bucket-imagenes-grupo2-0821-integrador.s3.amazonaws.com/imagenesHoteles/swimmingpool.jpg"
    }
  ]
}]
